pytest_skipper.py
pytest_skipper-0.1.3.dist-info/DESCRIPTION.rst
pytest_skipper-0.1.3.dist-info/METADATA
pytest_skipper-0.1.3.dist-info/RECORD
pytest_skipper-0.1.3.dist-info/WHEEL
pytest_skipper-0.1.3.dist-info/entry_points.txt
pytest_skipper-0.1.3.dist-info/metadata.json
pytest_skipper-0.1.3.dist-info/top_level.txt
