Metadata-Version: 2.0
Name: pytest-skipper
Version: 0.1.3
Summary: A plugin that selects only tests with changes in execution path
Home-page: https://github.com/quantus/pytest-skipper
Author: Pekka Pöyry
Author-email: pekka.poyry@gmail.com
License: MIT
Platform: UNKNOWN
Classifier: Development Status :: 3 - Alpha
Classifier: Framework :: Pytest
Classifier: Intended Audience :: Developers
Classifier: Topic :: Software Development :: Testing
Classifier: Programming Language :: Python
Classifier: Programming Language :: Python :: 2
Classifier: Programming Language :: Python :: 2.7
Classifier: Programming Language :: Python :: 3
Classifier: Programming Language :: Python :: 3.3
Classifier: Programming Language :: Python :: 3.4
Classifier: Programming Language :: Python :: 3.5
Classifier: Programming Language :: Python :: Implementation :: CPython
Classifier: Programming Language :: Python :: Implementation :: PyPy
Classifier: Operating System :: OS Independent
Classifier: License :: OSI Approved :: MIT License
Requires-Dist: GitPython (>=2.1.1)
Requires-Dist: coverage (>=4.2)
Requires-Dist: pytest (>=3.0.6)
